preconditiontogsq/__init__.py
preconditiontogsq/preconditiontogsq.py
preconditiontogsq-0.1.0.dist-info/LICENSE
preconditiontogsq-0.1.0.dist-info/METADATA
preconditiontogsq-0.1.0.dist-info/WHEEL
preconditiontogsq-0.1.0.dist-info/top_level.txt
preconditiontogsq-0.1.0.dist-info/RECORD
