Metadata-Version: 2.1
Name: preconditiontogsq
Version: 0.1.0
Summary: A Python library for converting Stardew Valley event preconditions to Game State Queries.
Author-email: AnotherPillow <redacted@email.xyz>
Project-URL: Homepage, https://github.com/AnotherPillow/preconditiontogsq
Project-URL: Bug Tracker, https://github.com/AnotherPillow/preconditiontogsq/issues
Classifier: Programming Language :: Python :: 3
Classifier: License :: OSI Approved :: GNU General Public License v3 (GPLv3)
Classifier: Operating System :: OS Independent
Requires-Python: >=3.8
License-File: LICENSE
